code/__init__.py
code/button.py
code/chinachess.py
code/computer.py
code/constants.py
code/pieces.py
code/imgs/s1/b_c.png
code/imgs/s1/b_j.png
code/imgs/s1/b_m.png
code/imgs/s1/b_p.png
code/imgs/s1/b_s (1).png
code/imgs/s1/b_s.png
code/imgs/s1/b_x.png
code/imgs/s1/bg.png
code/imgs/s1/r_c.png
code/imgs/s1/r_j.png
code/imgs/s1/r_m.png
code/imgs/s1/r_p.png
code/imgs/s1/r_s.png
code/imgs/s1/r_x.png
code/imgs/s1/r_z.png
code/imgs/s2/b_c.png
code/imgs/s2/b_j.png
code/imgs/s2/b_m.png
code/imgs/s2/b_p.png
code/imgs/s2/b_s.png
code/imgs/s2/b_x.png
code/imgs/s2/b_z.png
code/imgs/s2/bg.png
code/imgs/s2/r_c.png
code/imgs/s2/r_j.png
code/imgs/s2/r_m.png
code/imgs/s2/r_p.png
code/imgs/s2/r_s.png
code/imgs/s2/r_x.png
code/imgs/s2/r_z.png
chinachess-1.1.dist-info/METADATA
chinachess-1.1.dist-info/WHEEL
chinachess-1.1.dist-info/top_level.txt
chinachess-1.1.dist-info/RECORD
