Metadata-Version: 2.1
Name: chinachess
Version: 1.1
Summary: chinachess
Home-page: https://github.com/lindengxu68/chess
Author: lindengxu68
Author-email: lindengxu68@gmail.com
License: UNKNOWN
Platform: UNKNOWN
Requires-Python: >=3
Requires-Dist: pygame
